komtet_kassa_sdk/__init__.py
komtet_kassa_sdk/v1/__init__.py
komtet_kassa_sdk/v1/check.py
komtet_kassa_sdk/v1/client.py
komtet_kassa_sdk/v1/employee.py
komtet_kassa_sdk/v1/order.py
komtet_kassa_sdk/v1/lib/__init__.py
komtet_kassa_sdk/v1/lib/helpers.py
komtet_kassa_sdk/v2/__init__.py
komtet_kassa_sdk/v2/agent.py
komtet_kassa_sdk/v2/check.py
komtet_kassa_sdk/v2/client.py
komtet_kassa_sdk/v2/employee.py
komtet_kassa_sdk/v2/order.py
komtet_kassa_sdk/v2/lib/__init__.py
komtet_kassa_sdk/v2/lib/helpers.py
komtet_kassa_sdk-7.1.4.dist-info/LICENSE
komtet_kassa_sdk-7.1.4.dist-info/METADATA
komtet_kassa_sdk-7.1.4.dist-info/WHEEL
komtet_kassa_sdk-7.1.4.dist-info/top_level.txt
komtet_kassa_sdk-7.1.4.dist-info/RECORD
