Metadata-Version: 2.1
Name: komtet-kassa-sdk
Version: 7.1.4
Summary: Python SDK for KOMTET Kassa
Home-page: https://github.com/Komtet/komtet-kassa-python-sdk
Download-URL: https://pypi.python.org/pypi/komtet_kassa_sdk
Author: Motmom
Author-email: motmom.dev@gmail.com
License: MIT
Classifier: Intended Audience :: Developers
Classifier: Natural Language :: Russian
Classifier: Operating System :: OS Independent
Classifier: Programming Language :: Python
Classifier: Programming Language :: Python :: 2
Classifier: Programming Language :: Python :: 2.7
Classifier: Programming Language :: Python :: 3
Classifier: Programming Language :: Python :: 3.4
Classifier: Programming Language :: Python :: 3.5
Classifier: Programming Language :: Python :: 3.6
Classifier: Topic :: Software Development :: Libraries :: Python Modules
License-File: LICENSE
Requires-Dist: requests
